flet_desktop/__init__.py
flet_desktop/version.py
flet_desktop/app/flet-linux-arm64.tar.gz
flet_desktop-0.80.5.dist-info/METADATA
flet_desktop-0.80.5.dist-info/WHEEL
flet_desktop-0.80.5.dist-info/top_level.txt
flet_desktop-0.80.5.dist-info/RECORD
