Metadata-Version: 2.4
Name: flet-desktop
Version: 0.80.5
Summary: Flet Desktop client in Flutter
Author-email: "Appveyor Systems Inc." <hello@flet.dev>
License-Expression: Apache-2.0
Project-URL: Homepage, https://flet.dev
Project-URL: Repository, https://github.com/flet-dev/flet
Project-URL: Documentation, https://flet.dev/docs
Requires-Python: >=3.10
Requires-Dist: flet==0.80.5
